telethon_router/__init__.py
telethon_router/navigator.py
telethon_router/types/__init__.py
telethon_router/types/handler.py
telethon_router-0.1.1.dist-info/LICENSE
telethon_router-0.1.1.dist-info/METADATA
telethon_router-0.1.1.dist-info/WHEEL
telethon_router-0.1.1.dist-info/top_level.txt
telethon_router-0.1.1.dist-info/RECORD
