Metadata-Version: 2.2
Name: telethon_router
Version: 0.1.1
Summary: A library for building Telegram bots using routing similar to web pages.
Home-page: https://github.com/gabrielmrts/telethon_router
Author: Gabriel Lima
Author-email: gabrielmrtss@gmail.com
Classifier: Programming Language :: Python :: 3
Classifier: License :: OSI Approved :: MIT License
Classifier: Operating System :: OS Independent
Requires-Python: >=3.7
License-File: LICENSE
Requires-Dist: telethon
Dynamic: author
Dynamic: author-email
Dynamic: classifier
Dynamic: description
Dynamic: description-content-type
Dynamic: home-page
Dynamic: requires-dist
Dynamic: requires-python
Dynamic: summary
